darwin/__init__.py
darwin/backend_v2.py
darwin/cli.py
darwin/cli_functions.py
darwin/client.py
darwin/config.py
darwin/dataset/__init__.py
darwin/dataset/download_manager.py
darwin/dataset/identifier.py
darwin/dataset/local_dataset.py
darwin/dataset/release.py
darwin/dataset/remote_dataset.py
darwin/dataset/remote_dataset_v2.py
darwin/dataset/split_manager.py
darwin/dataset/storage_uploader.py
darwin/dataset/upload_manager.py
darwin/dataset/utils.py
darwin/datatypes.py
darwin/doc_enum.py
darwin/exceptions.py
darwin/exporter/__init__.py
darwin/exporter/exporter.py
darwin/exporter/formats/__init__.py
darwin/exporter/formats/coco.py
darwin/exporter/formats/cvat.py
darwin/exporter/formats/darwin.py
darwin/exporter/formats/dataloop.py
darwin/exporter/formats/helpers/__init__.py
darwin/exporter/formats/helpers/yolo_class_builder.py
darwin/exporter/formats/instance_mask.py
darwin/exporter/formats/mask.py
darwin/exporter/formats/nifti.py
darwin/exporter/formats/numpy_encoder.py
darwin/exporter/formats/pascalvoc.py
darwin/exporter/formats/semantic_mask.py
darwin/exporter/formats/semantic_mask_grey.py
darwin/exporter/formats/semantic_mask_index.py
darwin/exporter/formats/yolo.py
darwin/exporter/formats/yolo_segmented.py
darwin/extractor/__init__.py
darwin/extractor/video.py
darwin/future/__init__.py
darwin/future/core/__init__.py
darwin/future/core/client.py
darwin/future/core/datasets/__init__.py
darwin/future/core/datasets/create_dataset.py
darwin/future/core/datasets/get_dataset.py
darwin/future/core/datasets/list_datasets.py
darwin/future/core/datasets/remove_dataset.py
darwin/future/core/items/__init__.py
darwin/future/core/items/archive_items.py
darwin/future/core/items/assign_items.py
darwin/future/core/items/delete_items.py
darwin/future/core/items/get.py
darwin/future/core/items/move_items.py
darwin/future/core/items/move_items_to_folder.py
darwin/future/core/items/restore_items.py
darwin/future/core/items/set_item_layout.py
darwin_py-3.4.3.dist-info/LICENSE
darwin_py-3.4.3.dist-info/WHEEL
darwin_py-3.4.3.dist-info/entry_points.txt
darwin_py-3.4.3.dist-info/METADATA
darwin_py-3.4.3.dist-info/RECORD
